quadrature-0.1.2.dist-info/METADATA
quadrature-0.1.2.dist-info/WHEEL
quadrature/__init__.py
quadrature/quadrature.cpython-39-x86_64-linux-gnu.so
quadrature-0.1.2.dist-info/RECORD
